jupyter_cleaner/__init__.py
jupyter_cleaner/jupyter_cleaner.py
jupyter_cleaner-0.3.0.dist-info/entry_points.txt
jupyter_cleaner-0.3.0.dist-info/LICENSE
jupyter_cleaner-0.3.0.dist-info/METADATA
jupyter_cleaner-0.3.0.dist-info/WHEEL
jupyter_cleaner-0.3.0.dist-info/RECORD
