Metadata-Version: 2.1
Name: jupyter-cleaner
Version: 0.3.0
Summary: Easy git tracking of Jupyter lab files
Home-page: https://github.com/Stoops-ML/jupyter-cleaner
License: MIT
Author: Daniel Stoops
Author-email: danielstoops25@gmail.com
Maintainer: Daniel Stoops
Maintainer-email: danielstoops25@gmail.com
Requires-Python: >=3.8.1,<4.0.0
Classifier: License :: OSI Approved :: MIT License
Classifier: Programming Language :: Python :: 3
Classifier: Programming Language :: Python :: 3.9
Classifier: Programming Language :: Python :: 3.10
Classifier: Programming Language :: Python :: 3.11
Requires-Dist: black[jupyter] (>=23.3.0,<24.0.0)
Requires-Dist: reorder-python-imports (>=3.10.0,<4.0.0)
